django_pylibmc/__init__.py
django_pylibmc/memcached.py
django_pylibmc-0.6.1.dist-info/DESCRIPTION.rst
django_pylibmc-0.6.1.dist-info/METADATA
django_pylibmc-0.6.1.dist-info/metadata.json
django_pylibmc-0.6.1.dist-info/RECORD
django_pylibmc-0.6.1.dist-info/top_level.txt
django_pylibmc-0.6.1.dist-info/WHEEL
