Metadata-Version: 1.1
Name: django-pylibmc
Version: 0.6.1
Summary: Django cache backend using pylibmc
Home-page: https://github.com/django-pylibmc/django-pylibmc
Author: Jeff Balogh
Author-email: jbalogh@mozilla.com
License: BSD
Keywords: django cache pylibmc memcached
Platform: UNKNOWN
Classifier: Development Status :: 4 - Beta
Classifier: Environment :: Web Environment
Classifier: Environment :: Web Environment :: Mozilla
Classifier: Framework :: Django
Classifier: Intended Audience :: Developers
Classifier: License :: OSI Approved :: BSD License
Classifier: Operating System :: OS Independent
Classifier: Programming Language :: Python
Classifier: Programming Language :: Python :: 2
Classifier: Programming Language :: Python :: 2.7
Classifier: Programming Language :: Python :: 3
Classifier: Programming Language :: Python :: 3.4
Classifier: Programming Language :: Python :: 3.5
Classifier: Topic :: Software Development :: Libraries :: Python Modules
